envelope/__init__.py
envelope/environment.py
envelope/spaces.py
envelope/struct.py
envelope/typing.py
envelope/compat/__init__.py
envelope/compat/brax_envelope.py
envelope/compat/craftax_envelope.py
envelope/compat/gymnax_envelope.py
envelope/compat/jumanji_envelope.py
envelope/compat/kinetix_envelope.py
envelope/compat/mujoco_playground_envelope.py
envelope/compat/navix_envelope.py
envelope/wrappers/__init__.py
envelope/wrappers/autoreset_wrapper.py
envelope/wrappers/episode_statistics_wrapper.py
envelope/wrappers/normalization.py
envelope/wrappers/observation_normalization_wrapper.py
envelope/wrappers/state_injection_wrapper.py
envelope/wrappers/truncation_wrapper.py
envelope/wrappers/vmap_envs_wrapper.py
envelope/wrappers/vmap_wrapper.py
envelope/wrappers/wrapper.py
jax_envelope-0.1.1.dist-info/METADATA
jax_envelope-0.1.1.dist-info/WHEEL
jax_envelope-0.1.1.dist-info/licenses/LICENSE
jax_envelope-0.1.1.dist-info/RECORD
