Metadata-Version: 2.4
Name: jax-envelope
Version: 0.1.1
Summary: A JAX-native environment interface with powerful wrappers and adapters for popular RL environment suites
Project-URL: Homepage, https://github.com/keraJLi/envelope
Project-URL: Repository, https://github.com/keraJLi/envelope
Project-URL: Documentation, https://github.com/keraJLi/envelope#readme
Project-URL: Issues, https://github.com/keraJLi/envelope/issues
Project-URL: Changelog, https://github.com/keraJLi/envelope/releases
Author-email: Jarek Liesen <jarek.liesen@reuben.ox.ac.uk>
License: MIT
License-File: LICENSE
Keywords: deep-learning,environments,gymnasium,hardware-acceleration,jax,machine-learning,reinforcement-learning,vectorization
Classifier: Development Status :: 4 - Beta
Classifier: Intended Audience :: Developers
Classifier: Intended Audience :: Science/Research
Classifier: License :: OSI Approved :: MIT License
Classifier: Operating System :: OS Independent
Classifier: Programming Language :: Python :: 3
Classifier: Programming Language :: Python :: 3.12
Classifier: Topic :: Scientific/Engineering :: Artificial Intelligence
Classifier: Typing :: Typed
Requires-Python: >=3.12
Requires-Dist: jax>=0.5.0
